{
    "variants": {
        "wet=true":  [
            { "model": "mist:acid_grass_2_wet" },
            { "model": "mist:acid_grass_2_wet", "y": 90 },
            { "model": "mist:acid_grass_2_wet", "y": 180 },
            { "model": "mist:acid_grass_2_wet", "y": 270 }
        ],
        "wet=false": [
            { "model": "mist:acid_grass_2_dry" },
            { "model": "mist:acid_grass_2_dry", "y": 90 },
            { "model": "mist:acid_grass_2_dry", "y": 180 },
            { "model": "mist:acid_grass_2_dry", "y": 270 }
        ]
    }
}