{ 
    "type": "minecraft:crafting_shapeless",
    "group": "wood_step",
    "ingredients": [
        [
            {
                "item": "mist:r_tree_block",
                "data": 0
            },
            {
                "item": "mist:r_tree_block",
                "data": 4
            },
            {
                "item": "mist:r_tree_block",
                "data": 7
            },
            {
                "item": "mist:r_tree_block",
                "data": 8
            },
            {
                "item": "mist:r_tree_block",
                "data": 11
            }
        ]
    ],
    "result": {
        "item": "mist:r_tree_step",
        "count": 4
    }
}