{   "parent": "block/block",
    "textures": {
        "particle": "#side"
    },
    "elements": [
        {   "from": [ 4, 0, 4 ],
            "to":   [ 12, 16, 12 ],
            "faces": {
                "north": { "uv": [ 4, 0, 12, 16 ], "texture": "#side" },
                "south": { "uv": [ 4, 0, 12, 16 ], "texture": "#side" },
                "west":  { "uv": [ 4, 0, 12, 16 ], "texture": "#side" },
                "east":  { "uv": [ 4, 0, 12, 16 ], "texture": "#side" },
                "up":    { "uv": [ 4, 4, 12, 12 ], "texture": "#end", "cullface": "up" },
                "down":  { "uv": [ 4, 4, 12, 12 ], "texture": "#end", "cullface": "down" }
            }
        },
        {   "from": [ 0, 12, 7 ],
            "to": [ 16, 15, 9 ],
            "faces": {
                "down":  { "uv": [ 0, 0, 16, 2 ], "texture": "#plank" },
                "up":    { "uv": [ 0, 0, 16, 2 ], "texture": "#plank" },
                "east":  { "uv": [ 7, 1,  9, 4 ], "texture": "#plank", "cullface": "east" },
                "west":  { "uv": [ 7, 1,  9, 4 ], "texture": "#plank", "cullface": "west" },
                "south": { "uv": [ 0, 1, 16, 4 ], "texture": "#plank" },
                "north": { "uv": [ 0, 1, 16, 4 ], "texture": "#plank" }
            },
            "__comment": "top bar"
        },
        {   "from": [ 0, 6, 7 ],
            "to": [ 16, 9, 9 ],
            "faces": {
                "down":  { "uv": [ 0, 0, 16,  2 ], "texture": "#plank" },
                "up":    { "uv": [ 0, 0, 16,  2 ], "texture": "#plank" },
                "east":  { "uv": [ 7, 9,  9, 12 ], "texture": "#plank", "cullface": "east" },
                "west":  { "uv": [ 7, 9,  9, 12 ], "texture": "#plank", "cullface": "west" },
                "south": { "uv": [ 0, 9, 16, 12 ], "texture": "#plank" },
                "north": { "uv": [ 0, 9, 16, 12 ], "texture": "#plank" }
            },
            "__comment": "lower bar"
        }
    ],
    "display": {
        "gui": {
            "rotation": [ 30, 225, 0 ],
            "translation": [ 0, 0, 0],
            "scale":[ 0.625, 0.625, 0.625 ]
        },
        "thirdperson_righthand": {
            "rotation": [ 0, 100, 0 ],
            "translation": [ -1, 1, 0 ],
            "scale": [ 0.375, 0.375, 0.375 ]
        },
        "thirdperson_lefthand": {
            "rotation": [ 0, 100, 0 ],
            "translation": [ -1, 1, 0 ],
            "scale": [ 0.375, 0.375, 0.375 ]
        },
        "firstperson_righthand": {
            "rotation": [ 0, 0, 25 ],
            "translation": [ 1, 0, 0 ],
            "scale": [ 0.4, 0.4, 0.4 ]
        },
        "firstperson_lefthand": {
            "rotation": [ 0, 0, 25 ],
            "translation": [ 1, 0, 0 ],
            "scale": [ 0.4, 0.4, 0.4 ]
        }
    }
}